jgo/__init__.py
jgo/__main__.py
jgo/jgo.py
jgo/util.py
jgo-1.0.6.dist-info/METADATA
jgo-1.0.6.dist-info/WHEEL
jgo-1.0.6.dist-info/entry_points.txt
jgo-1.0.6.dist-info/top_level.txt
jgo-1.0.6.dist-info/RECORD
