Metadata-Version: 2.1
Name: jgo
Version: 1.0.6
Summary: Launch Java code from Python and the CLI, installation-free.
Author-email: SciJava developers <ctrueden@wisc.edu>
License: Unlicense
Project-URL: homepage, https://github.com/scijava/jgo
Project-URL: documentation, https://github.com/scijava/jgo/blob/main/README.md
Project-URL: source, https://github.com/scijava/jgo
Project-URL: download, https://pypi.org/project/jgo/
Project-URL: tracker, https://github.com/scijava/jgo/issues
Keywords: java,maven,launch
Classifier: Development Status :: 5 - Production/Stable
Classifier: Intended Audience :: Developers
Classifier: Intended Audience :: Education
Classifier: Intended Audience :: Science/Research
Classifier: Intended Audience :: System Administrators
Classifier: Programming Language :: Python :: 3 :: Only
Classifier: Programming Language :: Python :: 3.8
Classifier: Programming Language :: Python :: 3.9
Classifier: Programming Language :: Python :: 3.10
Classifier: Programming Language :: Python :: 3.11
Classifier: Programming Language :: Python :: 3.12
Classifier: License :: OSI Approved :: The Unlicense (Unlicense)
Classifier: Operating System :: Microsoft :: Windows
Classifier: Operating System :: Unix
Classifier: Operating System :: MacOS
Classifier: Topic :: Scientific/Engineering
Classifier: Topic :: Software Development :: Libraries :: Java Libraries
Classifier: Topic :: Software Development :: Libraries :: Python Modules
Classifier: Topic :: System :: Installation/Setup
Classifier: Topic :: System :: Shells
Classifier: Topic :: System :: System Shells
Classifier: Topic :: Utilities
Requires-Python: >=3.8
Requires-Dist: psutil
Provides-Extra: dev
Requires-Dist: autopep8; extra == "dev"
Requires-Dist: build; extra == "dev"
Requires-Dist: black; extra == "dev"
Requires-Dist: flake8; extra == "dev"
Requires-Dist: isort; extra == "dev"
Requires-Dist: pre-commit; extra == "dev"
Requires-Dist: pyflakes; extra == "dev"
Requires-Dist: pytest; extra == "dev"
Requires-Dist: pytest-cov; extra == "dev"
Requires-Dist: validate-pyproject[all]; extra == "dev"
